pymagisto/__init__.py
pymagisto/pymagisto.py
pymagisto-0.1.dist-info/LICENSE
pymagisto-0.1.dist-info/LICENSE.txt
pymagisto-0.1.dist-info/METADATA
pymagisto-0.1.dist-info/WHEEL
pymagisto-0.1.dist-info/top_level.txt
pymagisto-0.1.dist-info/RECORD
