Metadata-Version: 2.1
Name: pymagisto
Version: 0.1
Summary: Wrapper for magisto api
Home-page: https://github.com/alejandrojnm/pymagisto
Author: Alejandro JNM
Author-email: alejandrojnm@gmail.com
License: GPLv3
Platform: UNKNOWN
Classifier: Development Status :: 3 - Alpha
Classifier: License :: OSI Approved :: GNU General Public License v3 (GPLv3)
Classifier: Programming Language :: Python
Classifier: Programming Language :: Python :: 3.6
Classifier: Programming Language :: Python :: 3.7
Requires-Dist: requests
